{"columns":["iflag","safe_status","meaning","result_policy"],"records":[[1,"Converged","bracket collapsed with decreasing function magnitude","ok"],[2,"EndpointRoot","native current endpoint is exactly zero","ok"],[3,"PossibleSingularity","sign-changing bracket collapsed with increasing magnitude","ok_with_warning_status"],[4,"NoSignChange","native iteration collapsed without a sign change","ok_with_warning_status"],[5,"MaximumEvaluations","fixed native limit greater than 500 function evaluations reached","ok_with_warning_status"],["CPZERO/RPZERO:0","Converged","iterative polynomial-root driver completed and supplied per-root bounds","ok"],["CPZERO/RPZERO:1","InvalidInput","preflighted degree or leading coefficient was rejected","contract_violation"],["CPZERO/RPZERO:2","IterationLimitReached","best current roots are preserved; source does not calculate error bounds","ok_with_partial_result"],["CPQR79/RPQR79:0","Converged","companion-QR polynomial-root driver completed","ok"],["CPQR79/RPQR79:1","NoConvergence","source does not promise partial roots after its QR iteration limit","error_without_partial_result"],["CPQR79/RPQR79:2_or_3","InvalidInput","preflighted leading coefficient or degree was rejected","contract_violation"]],"schema_id":"slatec.safe-roots.status-map","schema_version":"1.0.0","snapshot_id":"complete-slatec-05078ebcb649b50e4435"}
