{
  "records": [
    {
      "assertions": [
        {
          "passed": true,
          "rule": "contains SAXPY"
        },
        {
          "observed": [
            "SAXPY"
          ],
          "passed": true,
          "rule": "excludes unrelated BLAS, special, roots, and FISHPACK drivers"
        }
      ],
      "assertions_passed": true,
      "kind": "complete-source-archive",
      "link_slatec_archive": true,
      "name": "all_saxpy_only",
      "requested_symbols": [
        "SAXPY"
      ]
    },
    {
      "assertions": [
        {
          "known_archive_symbols": 623,
          "observed": [],
          "passed": true,
          "rule": "requested symbol is retained"
        }
      ],
      "assertions_passed": true,
      "kind": "baseline",
      "link_slatec_archive": false,
      "name": "baseline_no_slatec",
      "requested_symbols": []
    },
    {
      "assertions": [
        {
          "observed": [],
          "passed": true,
          "rule": "all no-call links no SLATEC implementation symbol"
        }
      ],
      "assertions_passed": true,
      "kind": "all-no-call",
      "link_slatec_archive": true,
      "name": "raw_all_no_call",
      "requested_symbols": []
    },
    {
      "assertions": [
        {
          "passed": true,
          "rule": "contains DAI"
        },
        {
          "observed": [
            "D1MACH",
            "D9AIMP",
            "DAI",
            "DAIE",
            "DCSEVL",
            "FDUMP",
            "I1MACH",
            "INITDS",
            "J4SAVE",
            "XERCNT",
            "XERHLT",
            "XERMSG",
            "XERPRN",
            "XERSVE",
            "XGETUA"
          ],
          "passed": true,
          "rule": "excludes unrelated BLAS, special, roots, and FISHPACK drivers"
        }
      ],
      "assertions_passed": true,
      "kind": "raw",
      "link_slatec_archive": true,
      "name": "raw_dai_only",
      "requested_symbols": [
        "DAI"
      ]
    },
    {
      "assertions": [
        {
          "known_archive_symbols": 623,
          "observed": [
            "DDOT"
          ],
          "passed": true,
          "rule": "requested symbol is retained"
        }
      ],
      "assertions_passed": true,
      "kind": "raw",
      "link_slatec_archive": true,
      "name": "raw_ddot_only",
      "requested_symbols": [
        "DDOT"
      ]
    },
    {
      "assertions": [
        {
          "passed": true,
          "rule": "contains DGAMMA"
        },
        {
          "observed": [
            "D1MACH",
            "D9LGMC",
            "DCSEVL",
            "DGAMLM",
            "DGAMMA",
            "FDUMP",
            "I1MACH",
            "INITDS",
            "J4SAVE",
            "XERCNT",
            "XERHLT",
            "XERMSG",
            "XERPRN",
            "XERSVE",
            "XGETUA"
          ],
          "passed": true,
          "rule": "excludes unrelated BLAS, roots, and FISHPACK drivers"
        }
      ],
      "assertions_passed": true,
      "kind": "raw",
      "link_slatec_archive": true,
      "name": "raw_dgamma_only",
      "requested_symbols": [
        "DGAMMA"
      ]
    },
    {
      "assertions": [
        {
          "passed": true,
          "rule": "contains DGEMM"
        },
        {
          "observed": [
            "DGEMM",
            "FDUMP",
            "I1MACH",
            "J4SAVE",
            "LSAME",
            "XERBLA",
            "XERCNT",
            "XERHLT",
            "XERMSG",
            "XERPRN",
            "XERSVE",
            "XGETUA"
          ],
          "passed": true,
          "rule": "excludes unrelated Level 2/3 and other family drivers"
        }
      ],
      "assertions_passed": true,
      "kind": "raw",
      "link_slatec_archive": true,
      "name": "raw_dgemm_only",
      "requested_symbols": [
        "DGEMM"
      ]
    },
    {
      "assertions": [
        {
          "passed": true,
          "rule": "contains DGEMV"
        },
        {
          "observed": [
            "DGEMV",
            "FDUMP",
            "I1MACH",
            "J4SAVE",
            "LSAME",
            "XERBLA",
            "XERCNT",
            "XERHLT",
            "XERMSG",
            "XERPRN",
            "XERSVE",
            "XGETUA"
          ],
          "passed": true,
          "rule": "excludes unrelated Level 2/3 and other family drivers"
        }
      ],
      "assertions_passed": true,
      "kind": "raw",
      "link_slatec_archive": true,
      "name": "raw_dgemv_only",
      "requested_symbols": [
        "DGEMV"
      ]
    },
    {
      "assertions": [
        {
          "known_archive_symbols": 623,
          "observed": [
            "FDUMP",
            "FZERO",
            "I1MACH",
            "J4SAVE",
            "R1MACH",
            "XERCNT",
            "XERHLT",
            "XERMSG",
            "XERPRN",
            "XERSVE",
            "XGETUA"
          ],
          "passed": true,
          "rule": "requested symbol is retained"
        }
      ],
      "assertions_passed": true,
      "kind": "raw-address",
      "link_slatec_archive": true,
      "name": "raw_fzero_only",
      "requested_symbols": [
        "FZERO"
      ]
    },
    {
      "assertions": [
        {
          "known_archive_symbols": 623,
          "observed": [
            "COSGEN",
            "GENBUN",
            "HWSCRT",
            "PIMACH",
            "POISD2",
            "POISN2",
            "POISP2",
            "S1MERG",
            "SCOPY",
            "TRI3",
            "TRIX"
          ],
          "passed": true,
          "rule": "requested symbol is retained"
        }
      ],
      "assertions_passed": true,
      "kind": "raw-address",
      "link_slatec_archive": true,
      "name": "raw_hwscrt_only",
      "requested_symbols": [
        "HWSCRT"
      ]
    },
    {
      "assertions": [
        {
          "known_archive_symbols": 623,
          "observed": [
            "COSQB",
            "COSQB1",
            "COSQF",
            "COSQF1",
            "COSQI",
            "COST",
            "COSTI",
            "PIMACH",
            "POIS3D",
            "POS3D1",
            "RADB2",
            "RADB3",
            "RADB4",
            "RADB5",
            "RADBG",
            "RADF2",
            "RADF3",
            "RADF4",
            "RADF5",
            "RADFG",
            "RFFTB",
            "RFFTB1",
            "RFFTF",
            "RFFTF1",
            "RFFTI",
            "RFFTI1",
            "SINQB",
            "SINQF",
            "SINQI",
            "SINT",
            "SINTI",
            "TRIDQ"
          ],
          "passed": true,
          "rule": "requested symbol is retained"
        }
      ],
      "assertions_passed": true,
      "kind": "raw-address",
      "link_slatec_archive": true,
      "name": "raw_pois3d_only",
      "requested_symbols": [
        "POIS3D"
      ]
    },
    {
      "assertions": [
        {
          "known_archive_symbols": 623,
          "observed": [
            "DDOT",
            "SAXPY"
          ],
          "passed": true,
          "rule": "requested symbol is retained"
        }
      ],
      "assertions_passed": true,
      "kind": "raw",
      "link_slatec_archive": true,
      "name": "raw_saxpy_ddot",
      "requested_symbols": [
        "SAXPY",
        "DDOT"
      ]
    },
    {
      "assertions": [
        {
          "passed": true,
          "rule": "contains SAXPY"
        },
        {
          "observed": [
            "SAXPY"
          ],
          "passed": true,
          "rule": "excludes unrelated BLAS, special, roots, and FISHPACK drivers"
        }
      ],
      "assertions_passed": true,
      "kind": "raw",
      "link_slatec_archive": true,
      "name": "raw_saxpy_only",
      "requested_symbols": [
        "SAXPY"
      ]
    },
    {
      "assertions": [
        {
          "passed": true,
          "rule": "contains DAI"
        },
        {
          "observed": [
            "D1MACH",
            "D9AIMP",
            "DAI",
            "DAIE",
            "DCSEVL",
            "FDUMP",
            "I1MACH",
            "INITDS",
            "J4SAVE",
            "XERCNT",
            "XERHLT",
            "XERMSG",
            "XERPRN",
            "XERSVE",
            "XGETUA"
          ],
          "passed": true,
          "rule": "excludes unrelated BLAS, special, roots, and FISHPACK drivers"
        }
      ],
      "assertions_passed": true,
      "kind": "safe",
      "link_slatec_archive": true,
      "name": "safe_airy_only",
      "requested_symbols": [
        "DAI"
      ]
    },
    {
      "assertions": [
        {
          "observed": [],
          "passed": true,
          "rule": "all no-call links no SLATEC implementation symbol"
        }
      ],
      "assertions_passed": true,
      "kind": "all-no-call",
      "link_slatec_archive": true,
      "name": "safe_all_no_call",
      "requested_symbols": []
    },
    {
      "assertions": [
        {
          "passed": true,
          "rule": "contains DDOT"
        },
        {
          "observed": [
            "DDOT"
          ],
          "passed": true,
          "rule": "excludes unrelated BLAS and other family drivers"
        }
      ],
      "assertions_passed": true,
      "kind": "safe",
      "link_slatec_archive": true,
      "name": "safe_ddot_only",
      "requested_symbols": [
        "DDOT"
      ]
    },
    {
      "assertions": [
        {
          "passed": true,
          "rule": "contains DGEMM"
        },
        {
          "observed": [
            "DGEMM",
            "FDUMP",
            "I1MACH",
            "J4SAVE",
            "LSAME",
            "XERBLA",
            "XERCNT",
            "XERHLT",
            "XERMSG",
            "XERPRN",
            "XERSVE",
            "XGETUA"
          ],
          "passed": true,
          "rule": "excludes unrelated Level 2/3 and other family drivers"
        }
      ],
      "assertions_passed": true,
      "kind": "safe",
      "link_slatec_archive": true,
      "name": "safe_dgemm_only",
      "requested_symbols": [
        "DGEMM"
      ]
    },
    {
      "assertions": [
        {
          "passed": true,
          "rule": "contains DGEMV"
        },
        {
          "observed": [
            "DGEMV",
            "FDUMP",
            "I1MACH",
            "J4SAVE",
            "LSAME",
            "XERBLA",
            "XERCNT",
            "XERHLT",
            "XERMSG",
            "XERPRN",
            "XERSVE",
            "XGETUA"
          ],
          "passed": true,
          "rule": "excludes unrelated Level 2/3 and other family drivers"
        }
      ],
      "assertions_passed": true,
      "kind": "safe",
      "link_slatec_archive": true,
      "name": "safe_dgemv_only",
      "requested_symbols": [
        "DGEMV"
      ]
    },
    {
      "assertions": [
        {
          "passed": true,
          "rule": "contains HWSCRT"
        },
        {
          "observed": [
            "COSGEN",
            "GENBUN",
            "HWSCRT",
            "PIMACH",
            "POISD2",
            "POISN2",
            "POISP2",
            "S1MERG",
            "SCOPY",
            "TRI3",
            "TRIX"
          ],
          "passed": true,
          "rule": "excludes unrelated BLAS, special, roots, and POIS3D drivers"
        }
      ],
      "assertions_passed": true,
      "kind": "safe",
      "link_slatec_archive": true,
      "name": "safe_fishpack_hwscrt_only",
      "requested_symbols": [
        "HWSCRT"
      ]
    },
    {
      "assertions": [
        {
          "passed": true,
          "rule": "contains FZERO"
        },
        {
          "observed": [
            "D1MACH",
            "DFZERO",
            "FDUMP",
            "FZERO",
            "I1MACH",
            "J4SAVE",
            "R1MACH",
            "XERCNT",
            "XERHLT",
            "XERMSG",
            "XERPRN",
            "XERSVE",
            "XGETUA"
          ],
          "passed": true,
          "rule": "excludes unrelated BLAS, special, and FISHPACK drivers"
        }
      ],
      "assertions_passed": true,
      "kind": "safe",
      "link_slatec_archive": true,
      "name": "safe_roots_only",
      "requested_symbols": [
        "FZERO"
      ]
    },
    {
      "assertions": [
        {
          "passed": true,
          "rule": "contains SAXPY"
        },
        {
          "observed": [
            "SAXPY"
          ],
          "passed": true,
          "rule": "excludes unrelated BLAS, special, roots, and FISHPACK drivers"
        }
      ],
      "assertions_passed": true,
      "kind": "safe",
      "link_slatec_archive": true,
      "name": "safe_saxpy_only",
      "requested_symbols": [
        "SAXPY"
      ]
    },
    {
      "assertions": [
        {
          "passed": true,
          "rule": "contains DGAMMA"
        },
        {
          "observed": [
            "D1MACH",
            "D9LGMC",
            "DCSEVL",
            "DGAMLM",
            "DGAMMA",
            "FDUMP",
            "I1MACH",
            "INITDS",
            "J4SAVE",
            "XERCNT",
            "XERHLT",
            "XERMSG",
            "XERPRN",
            "XERSVE",
            "XGETUA"
          ],
          "passed": true,
          "rule": "excludes unrelated BLAS, roots, and FISHPACK drivers"
        }
      ],
      "assertions_passed": true,
      "kind": "safe",
      "link_slatec_archive": true,
      "name": "safe_special_only",
      "requested_symbols": [
        "DGAMMA"
      ]
    }
  ],
  "schema_id": "slatec-rs/native-link-probe-results",
  "snapshot_id": "complete-slatec-05078ebcb649b50e4435"
}
